boring_math/abstract_algebra/__init__.py
boring_math/abstract_algebra/py.typed
boring_math/abstract_algebra/algebras/__init__.py
boring_math/abstract_algebra/algebras/abelian_group.py
boring_math/abstract_algebra/algebras/commutative_monoid.py
boring_math/abstract_algebra/algebras/commutative_ring.py
boring_math/abstract_algebra/algebras/commutative_semigroup.py
boring_math/abstract_algebra/algebras/field.py
boring_math/abstract_algebra/algebras/group.py
boring_math/abstract_algebra/algebras/monoid.py
boring_math/abstract_algebra/algebras/ring.py
boring_math/abstract_algebra/algebras/semigroup.py
boring_math/abstract_algebra/properties/__init__.py
boring_math/abstract_algebra/properties/orderings.py
boring_math_abstract_algebra-1.1.0.dist-info/licenses/LICENSE
boring_math_abstract_algebra-1.1.0.dist-info/WHEEL
boring_math_abstract_algebra-1.1.0.dist-info/METADATA
boring_math_abstract_algebra-1.1.0.dist-info/RECORD
