Metadata-Version: 2.4
Name: boring-math-abstract-algebra
Version: 1.1.0
Summary: Abstract Algebra Library
Keywords: algebra,abstract algebra
Author-email: "Geoffrey R. Scheller" <geoffrey@scheller.com>
Requires-Python: >=3.13
Classifier: Development Status :: 3 - Alpha
Classifier: Framework :: Pytest
Classifier: Intended Audience :: Education
Classifier: License :: OSI Approved :: Apache Software License
Classifier: Operating System :: OS Independent
Classifier: Programming Language :: Python :: 3.13
Classifier: Typing :: Typed
License-File: LICENSE
Requires-Dist: pythonic-fp-fptools>=5.2.0
Requires-Dist: pytest>=8.4.1 ; extra == "test"
Requires-Dist: numpy>=2.3.4 ; extra == "test"
Requires-Dist: pythonic-fp-numpy>=0.1.1 ; extra == "test"
Project-URL: Changelog, https://github.com/grscheller/boring-math-abstract-algebra/blob/main/CHANGELOG.md
Project-URL: Documentation, https://grscheller.github.io/boring-math/abstract-algebra
Project-URL: Homepage, https://grscheller.github.io/boring-math
Project-URL: Source, https://github.com/grscheller/boring-math-abstract-algebra
Provides-Extra: test
